colorutils/__init__.py
colorutils/colorutils.py
colorutils/convert.py
colorutils/equality.py
colorutils/exceptions.py
colorutils/static.py
colorutils-0.3.0.dist-info/LICENSE.txt
colorutils-0.3.0.dist-info/METADATA
colorutils-0.3.0.dist-info/WHEEL
colorutils-0.3.0.dist-info/top_level.txt
colorutils-0.3.0.dist-info/RECORD
