Metadata-Version: 1.1
Name: colorutils
Version: 0.3.0
Summary: A utility for working with colors in Python.
Home-page: https://github.com/edaniszewski/colorutils
Author: Erick Daniszewski
Author-email: edaniszewski@gmail.com
License: MIT
Download-URL: https://github.com/edaniszewski/colorutils/releases/tag/0.1
Keywords: color,color manipulation,color conversion,color tools
Platform: UNKNOWN
Classifier: Intended Audience :: Developers
Classifier: License :: OSI Approved :: MIT License
Classifier: Natural Language :: English
Classifier: Programming Language :: Python
Classifier: Programming Language :: Python :: 2
Classifier: Programming Language :: Python :: 2.7
Classifier: Topic :: Utilities
